MANIFEST.in
setup.py
VlcTVStation.egg-info/PKG-INFO
VlcTVStation.egg-info/SOURCES.txt
VlcTVStation.egg-info/dependency_links.txt
VlcTVStation.egg-info/entry_points.txt
VlcTVStation.egg-info/not-zip-safe
VlcTVStation.egg-info/requires.txt
VlcTVStation.egg-info/top_level.txt
vlctvstation/__init__.py
vlctvstation/auth.py
vlctvstation/default.cfg
vlctvstation/mdict.py
vlctvstation/settings.py
vlctvstation/vlc.py
vlctvstation/vlctvstation.py
vlctvstation/static/jquery.js
vlctvstation/static/script.js
vlctvstation/static/style.css
vlctvstation/static/bootstrap/css/bootstrap-theme.css
vlctvstation/static/bootstrap/css/bootstrap-theme.min.css
vlctvstation/static/bootstrap/css/bootstrap.css
vlctvstation/static/bootstrap/css/bootstrap.min.css
vlctvstation/static/bootstrap/fonts/glyphicons-halflings-regular.eot
vlctvstation/static/bootstrap/fonts/glyphicons-halflings-regular.svg
vlctvstation/static/bootstrap/fonts/glyphicons-halflings-regular.ttf
vlctvstation/static/bootstrap/fonts/glyphicons-halflings-regular.woff
vlctvstation/static/bootstrap/js/bootstrap.js
vlctvstation/static/bootstrap/js/bootstrap.min.js
vlctvstation/static/bootstrap/js/modal.js
vlctvstation/static/images/key.png
vlctvstation/static/images/user.png
vlctvstation/templates/addjob.html
vlctvstation/templates/auth.html
vlctvstation/templates/editjob.html
vlctvstation/templates/gethash.html
vlctvstation/templates/jobs.html
vlctvstation/templates/main.html
vlctvstation/templates/modal.html
vlctvstation/templates/open.html
vlctvstation/translations/en/LC_MESSAGES/vlctvstation.mo
vlctvstation/translations/ru/LC_MESSAGES/vlctvstation.mo