Metadata-Version: 1.0
Name: VlcTVStation
Version: 1.0
Summary: Wanna build a tv station in your village? But pay nothing for software, which costs huge money, and nobody cares you have only 5 viewers, well, welcome to vlctvstation then.
Home-page: UNKNOWN
Author: Maxim Nikitenko
Author-email: sets88@mail.ru
License: UNKNOWN
Platform: UNKNOWN
